{
	"char": {
		"name": "Whohy Uscofraiv",
		"bio": "",
		"gmnotes": "",
		"avatar": "",
		"inplayerjournals": "",
		"controlledby": "",
		"defaulttoken": "",
		"tags": "",
		"archived": false,
		"attrorder": "",
		"abilorder": "",
		"mancerdata": "{}",
		"id": "-KlzbIXtf1bzav5NdpqU",
		"attribs": [
			{
				"name": "sheet_processing_complete",
				"current": "",
				"max": "",
				"id": "-KoAFtbOy2ArZKpwhADF"
			},
			{
				"name": "edit_mode",
				"current": "on",
				"max": "",
				"id": "-KoAFtbTu-O9juEJNu2a"
			},
			{
				"name": "version",
				"current": "15.4.0",
				"max": "",
				"id": "-KoAFtbYcN11LSrB6weq"
			},
			{
				"name": "character_sheet",
				"current": "Shaped v15.4.0",
				"max": "",
				"id": "-KoAFtbe_efNTRIshPIX"
			},
			{
				"name": "strength_mod",
				"current": 0,
				"max": "",
				"id": "-KoAFtbsUQHAMQbWVmR-"
			},
			{
				"name": "dexterity_mod",
				"current": 0,
				"max": "",
				"id": "-KoAFtbwk8sjUneU-Me5"
			},
			{
				"name": "constitution_mod",
				"current": 0,
				"max": "",
				"id": "-KoAFtc-u-1d478SLsD6"
			},
			{
				"name": "intelligence_mod",
				"current": 0,
				"max": "",
				"id": "-KoAFtc2AUpS8OorZTRL"
			},
			{
				"name": "wisdom_mod",
				"current": 0,
				"max": "",
				"id": "-KoAFtc6tJap8uHDzaaX"
			},
			{
				"name": "charisma_mod",
				"current": 0,
				"max": "",
				"id": "-KoAFtc9PLz8OP9tlTUY"
			},
			{
				"name": "honor_mod",
				"current": 0,
				"max": "",
				"id": "-KoAFtcCCrfZbI4Hvgl4"
			},
			{
				"name": "sanity_mod",
				"current": 0,
				"max": "",
				"id": "-KoAFtcH280zzQiyfZmP"
			},
			{
				"name": "strength_check_formula",
				"current": "{{roll1=[[@{shaped_d20}@{d20_mod} + 0[str]]]}}",
				"max": "",
				"id": "-KoAFtcLBWCBC3QG4Xee"
			},
			{
				"name": "dexterity_check_formula",
				"current": "{{roll1=[[@{shaped_d20}@{d20_mod} + 0[dex]]]}}",
				"max": "",
				"id": "-KoAFtcOeNPfcHnyKiib"
			},
			{
				"name": "constitution_check_formula",
				"current": "{{roll1=[[@{shaped_d20}@{d20_mod} + 0[con]]]}}",
				"max": "",
				"id": "-KoAFtcRszTKaAHUDRhX"
			},
			{
				"name": "intelligence_check_formula",
				"current": "{{roll1=[[@{shaped_d20}@{d20_mod} + 0[int]]]}}",
				"max": "",
				"id": "-KoAFtcVs2D7Gr57uoRL"
			},
			{
				"name": "wisdom_check_formula",
				"current": "{{roll1=[[@{shaped_d20}@{d20_mod} + 0[wis]]]}}",
				"max": "",
				"id": "-KoAFtcYr9ZPLiu70_P9"
			},
			{
				"name": "charisma_check_formula",
				"current": "{{roll1=[[@{shaped_d20}@{d20_mod} + 0[cha]]]}}",
				"max": "",
				"id": "-KoAFtca7i3ksW_7lpfA"
			},
			{
				"name": "honor_check_formula",
				"current": "{{roll1=[[@{shaped_d20}@{d20_mod} + 0[hon]]]}}",
				"max": "",
				"id": "-KoAFtcdzLBTySmGN48y"
			},
			{
				"name": "sanity_check_formula",
				"current": "{{roll1=[[@{shaped_d20}@{d20_mod} + 0[san]]]}}",
				"max": "",
				"id": "-KoAFtcfZ70epOR3QOKe"
			},
			{
				"name": "strength_calculated",
				"current": 10,
				"max": "",
				"id": "-KoAFtclyXaO64szp-ya"
			},
			{
				"name": "strength_check_mod_with_sign",
				"current": "+0",
				"max": "",
				"id": "-KoAFtcpRd81xJzcMmI0"
			},
			{
				"name": "finesse_mod",
				"current": 0,
				"max": "",
				"id": "-KoAFtcsvdDKuQFIzNls"
			},
			{
				"name": "dexterity_calculated",
				"current": 10,
				"max": "",
				"id": "-KoAFtcv5AzkaoRZYiG_"
			},
			{
				"name": "dexterity_check_mod_with_sign",
				"current": "+0",
				"max": "",
				"id": "-KoAFtcybZ_4WzJ9G81D"
			},
			{
				"name": "constitution_calculated",
				"current": 10,
				"max": "",
				"id": "-KoAFtd0h_A-ihfZofQs"
			},
			{
				"name": "constitution_check_mod_with_sign",
				"current": "+0",
				"max": "",
				"id": "-KoAFtd33yoLXFhB_f1b"
			},
			{
				"name": "intelligence_calculated",
				"current": 10,
				"max": "",
				"id": "-KoAFtd5fbiAT-dMlcYk"
			},
			{
				"name": "intelligence_check_mod_with_sign",
				"current": "+0",
				"max": "",
				"id": "-KoAFtd818f4ioYRoEdh"
			},
			{
				"name": "wisdom_calculated",
				"current": 10,
				"max": "",
				"id": "-KoAFtdCaAV-zGVv4_mn"
			},
			{
				"name": "wisdom_check_mod_with_sign",
				"current": "+0",
				"max": "",
				"id": "-KoAFtdFZyQz4zblfKUf"
			},
			{
				"name": "charisma_calculated",
				"current": 10,
				"max": "",
				"id": "-KoAFtdJkDIvAs5DrOSv"
			},
			{
				"name": "charisma_check_mod_with_sign",
				"current": "+0",
				"max": "",
				"id": "-KoAFtdLkVS8QcEcOJxR"
			},
			{
				"name": "honor_calculated",
				"current": 10,
				"max": "",
				"id": "-KoAFtdPFR8I7kBJHG7L"
			},
			{
				"name": "honor_check_mod_with_sign",
				"current": "+0",
				"max": "",
				"id": "-KoAFtdUOqZHlEQ6Ia1l"
			},
			{
				"name": "sanity_calculated",
				"current": 10,
				"max": "",
				"id": "-KoAFtdYTikUtSbtrVuN"
			},
			{
				"name": "sanity_check_mod_with_sign",
				"current": "+0",
				"max": "",
				"id": "-KoAFtdbFGriVnbo7_4J"
			},
			{
				"name": "initiative_formula",
				"current": "@{selected|initiative_roll}@{d20_mod} &{tracker} + 0[dex]",
				"max": "",
				"id": "-KoAFth2_deQbS9ZVnrk"
			},
			{
				"name": "initiative",
				"current": "+0",
				"max": "",
				"id": "-KoAFth6VRv5I4N3Xm5F"
			},
			{
				"name": "strength_saving_throw_formula",
				"current": "{{roll1=[[@{shaped_d20}@{d20_mod} + 0[str]]]}}",
				"max": "",
				"id": "-KoAFthCqsVnniogfgAl"
			},
			{
				"name": "dexterity_saving_throw_formula",
				"current": "{{roll1=[[@{shaped_d20}@{d20_mod} + 0[dex]]]}}",
				"max": "",
				"id": "-KoAFthHSv837p-0goY4"
			},
			{
				"name": "constitution_saving_throw_formula",
				"current": "{{roll1=[[@{shaped_d20}@{d20_mod} + 0[con]]]}}",
				"max": "",
				"id": "-KoAFthLHBrJaQv5o50P"
			},
			{
				"name": "intelligence_saving_throw_formula",
				"current": "{{roll1=[[@{shaped_d20}@{d20_mod} + 0[int]]]}}",
				"max": "",
				"id": "-KoAFthOvgnApLioz44U"
			},
			{
				"name": "wisdom_saving_throw_formula",
				"current": "{{roll1=[[@{shaped_d20}@{d20_mod} + 0[wis]]]}}",
				"max": "",
				"id": "-KoAFthSptxb4_EV62t_"
			},
			{
				"name": "charisma_saving_throw_formula",
				"current": "{{roll1=[[@{shaped_d20}@{d20_mod} + 0[cha]]]}}",
				"max": "",
				"id": "-KoAFthWTp2Q-tKKHuiy"
			},
			{
				"name": "honor_saving_throw_formula",
				"current": "{{roll1=[[@{shaped_d20}@{d20_mod} + 0[hon]]]}}",
				"max": "",
				"id": "-KoAFth_V73LFFP7oNLn"
			},
			{
				"name": "sanity_saving_throw_formula",
				"current": "{{roll1=[[@{shaped_d20}@{d20_mod} + 0[san]]]}}",
				"max": "",
				"id": "-KoAFthdAb7u04FQYyOC"
			},
			{
				"name": "death_saving_throw_formula",
				"current": "{{roll1=[[@{shaped_d20}@{d20_mod} + ]]}}",
				"max": "",
				"id": "-KoAFthgnGyHY_sIwPms"
			},
			{
				"name": "death_saving_throw_mod_with_sign",
				"current": "+0",
				"max": "",
				"id": "-KoAFthkhNb7jSq5YSqS"
			},
			{
				"name": "fortitude_saving_throw_formula",
				"current": "{{roll1=[[@{shaped_d20}@{d20_mod} + ]]}}",
				"max": "",
				"id": "-KoAFthu8Hcek0CroRDH"
			},
			{
				"name": "reflex_saving_throw_formula",
				"current": "{{roll1=[[@{shaped_d20}@{d20_mod} + ]]}}",
				"max": "",
				"id": "-KoAFthzRSQIOqDFes5f"
			},
			{
				"name": "will_saving_throw_formula",
				"current": "{{roll1=[[@{shaped_d20}@{d20_mod} + ]]}}",
				"max": "",
				"id": "-KoAFti2gzg1Ah1f2F__"
			},
			{
				"name": "repeating_skill_-KoAFth4EshB524jmYyt_storage_name",
				"current": "ACROBATICS",
				"max": "",
				"id": "-KoAFtiJ0IF6hSWON18E"
			},
			{
				"name": "repeating_skill_-KoAFth4EshB524jmYyt_name",
				"current": "Acrobatics",
				"max": "",
				"id": "-KoAFtiNhJ8K3xcsMr_V"
			},
			{
				"name": "repeating_skill_-KoAFth4EshB524jmYyt_ability",
				"current": "DEX",
				"max": "",
				"id": "-KoAFtiRXaZbMklr2Pj3"
			},
			{
				"name": "repeating_skill_-KoAFth4EshB524jmYyu_storage_name",
				"current": "ANIMALHANDLING",
				"max": "",
				"id": "-KoAFtiUyQq0o2kByBXG"
			},
			{
				"name": "repeating_skill_-KoAFth4EshB524jmYyu_name",
				"current": "Animal Handling",
				"max": "",
				"id": "-KoAFtiZbX4yY4T17d5u"
			},
			{
				"name": "repeating_skill_-KoAFth4EshB524jmYyu_ability",
				"current": "WIS",
				"max": "",
				"id": "-KoAFtid1vJPhB_LemUu"
			},
			{
				"name": "repeating_skill_-KoAFth4EshB524jmYyv_storage_name",
				"current": "ARCANA",
				"max": "",
				"id": "-KoAFtiiIJXSYF08ccgL"
			},
			{
				"name": "repeating_skill_-KoAFth4EshB524jmYyv_name",
				"current": "Arcana",
				"max": "",
				"id": "-KoAFtim7aN8GEeGfmZA"
			},
			{
				"name": "repeating_skill_-KoAFth4EshB524jmYyv_ability",
				"current": "INT",
				"max": "",
				"id": "-KoAFtircTVVRiumOT5F"
			},
			{
				"name": "repeating_skill_-KoAFth59aXPKNZYkgIg_storage_name",
				"current": "ATHLETICS",
				"max": "",
				"id": "-KoAFtivicv8rUWkM0e4"
			},
			{
				"name": "repeating_skill_-KoAFth59aXPKNZYkgIg_name",
				"current": "Athletics",
				"max": "",
				"id": "-KoAFtizS8TZy387UABH"
			},
			{
				"name": "repeating_skill_-KoAFth59aXPKNZYkgIg_ability",
				"current": "STR",
				"max": "",
				"id": "-KoAFtj2ecchMx1Eob7w"
			},
			{
				"name": "repeating_skill_-KoAFth59aXPKNZYkgIh_storage_name",
				"current": "DECEPTION",
				"max": "",
				"id": "-KoAFtj7kz-6HhjwOmrk"
			},
			{
				"name": "repeating_skill_-KoAFth59aXPKNZYkgIh_name",
				"current": "Deception",
				"max": "",
				"id": "-KoAFtjANV4do4eBvB23"
			},
			{
				"name": "repeating_skill_-KoAFth59aXPKNZYkgIh_ability",
				"current": "CHA",
				"max": "",
				"id": "-KoAFtjEZUhWFw4UONbM"
			},
			{
				"name": "repeating_skill_-KoAFth59aXPKNZYkgIi_storage_name",
				"current": "HISTORY",
				"max": "",
				"id": "-KoAFtjJUHY4wbrNKbkT"
			},
			{
				"name": "repeating_skill_-KoAFth59aXPKNZYkgIi_name",
				"current": "History",
				"max": "",
				"id": "-KoAFtjMqyXJ0niz9eBr"
			},
			{
				"name": "repeating_skill_-KoAFth59aXPKNZYkgIi_ability",
				"current": "INT",
				"max": "",
				"id": "-KoAFtjPOioFUc_ZRMu8"
			},
			{
				"name": "repeating_skill_-KoAFth59aXPKNZYkgIj_storage_name",
				"current": "INSIGHT",
				"max": "",
				"id": "-KoAFtjSU_P53P7gR9EQ"
			},
			{
				"name": "repeating_skill_-KoAFth59aXPKNZYkgIj_name",
				"current": "Insight",
				"max": "",
				"id": "-KoAFtjWOgx-I2ctFS_U"
			},
			{
				"name": "repeating_skill_-KoAFth59aXPKNZYkgIj_ability",
				"current": "WIS",
				"max": "",
				"id": "-KoAFtjZf-vWLogfVxO_"
			},
			{
				"name": "repeating_skill_-KoAFth59aXPKNZYkgIk_storage_name",
				"current": "INTIMIDATION",
				"max": "",
				"id": "-KoAFtjbxROyiGfMyBme"
			},
			{
				"name": "repeating_skill_-KoAFth59aXPKNZYkgIk_name",
				"current": "Intimidation",
				"max": "",
				"id": "-KoAFtjfSlcWI_S2W4j7"
			},
			{
				"name": "repeating_skill_-KoAFth59aXPKNZYkgIk_ability",
				"current": "CHA",
				"max": "",
				"id": "-KoAFtjirDBKIrpVl8CB"
			},
			{
				"name": "repeating_skill_-KoAFth59aXPKNZYkgIl_storage_name",
				"current": "INVESTIGATION",
				"max": "",
				"id": "-KoAFtjlLo3UXD5Dk4_3"
			},
			{
				"name": "repeating_skill_-KoAFth59aXPKNZYkgIl_name",
				"current": "Investigation",
				"max": "",
				"id": "-KoAFtjpUF4gLap5LkpL"
			},
			{
				"name": "repeating_skill_-KoAFth59aXPKNZYkgIl_ability",
				"current": "INT",
				"max": "",
				"id": "-KoAFtjssX05eZJyFaEZ"
			},
			{
				"name": "repeating_skill_-KoAFth59aXPKNZYkgIm_storage_name",
				"current": "MEDICINE",
				"max": "",
				"id": "-KoAFtjwKzCuRwUefGly"
			},
			{
				"name": "repeating_skill_-KoAFth59aXPKNZYkgIm_name",
				"current": "Medicine",
				"max": "",
				"id": "-KoAFtjz2cfKg0bdvBGT"
			},
			{
				"name": "repeating_skill_-KoAFth59aXPKNZYkgIm_ability",
				"current": "WIS",
				"max": "",
				"id": "-KoAFtk2sYApaUyx-0ny"
			},
			{
				"name": "repeating_skill_-KoAFth59aXPKNZYkgIn_storage_name",
				"current": "NATURE",
				"max": "",
				"id": "-KoAFtk6BULxol3cT8xN"
			},
			{
				"name": "repeating_skill_-KoAFth59aXPKNZYkgIn_name",
				"current": "Nature",
				"max": "",
				"id": "-KoAFtkDPq3fO01RrkJ2"
			},
			{
				"name": "repeating_skill_-KoAFth59aXPKNZYkgIn_ability",
				"current": "INT",
				"max": "",
				"id": "-KoAFtkHsq5YbxCgAKi2"
			},
			{
				"name": "repeating_skill_-KoAFth59aXPKNZYkgIo_storage_name",
				"current": "PERCEPTION",
				"max": "",
				"id": "-KoAFtkL5FYrv6UMRO96"
			},
			{
				"name": "repeating_skill_-KoAFth59aXPKNZYkgIo_name",
				"current": "Perception",
				"max": "",
				"id": "-KoAFtkPeaQXxI2Xmsdj"
			},
			{
				"name": "repeating_skill_-KoAFth59aXPKNZYkgIo_ability",
				"current": "WIS",
				"max": "",
				"id": "-KoAFtkTv8tum4bQd7M-"
			},
			{
				"name": "repeating_skill_-KoAFth59aXPKNZYkgIp_storage_name",
				"current": "PERFORMANCE",
				"max": "",
				"id": "-KoAFtkYqt1JrnO5Obyd"
			},
			{
				"name": "repeating_skill_-KoAFth59aXPKNZYkgIp_name",
				"current": "Performance",
				"max": "",
				"id": "-KoAFtkahU82BHKfO6Yg"
			},
			{
				"name": "repeating_skill_-KoAFth59aXPKNZYkgIp_ability",
				"current": "CHA",
				"max": "",
				"id": "-KoAFtkd-NaN61hlowJU"
			},
			{
				"name": "repeating_skill_-KoAFth59aXPKNZYkgIq_storage_name",
				"current": "PERSUASION",
				"max": "",
				"id": "-KoAFtkhXTlKUdWcxblD"
			},
			{
				"name": "repeating_skill_-KoAFth59aXPKNZYkgIq_name",
				"current": "Persuasion",
				"max": "",
				"id": "-KoAFtkk1g6HQjlDXSpy"
			},
			{
				"name": "repeating_skill_-KoAFth59aXPKNZYkgIq_ability",
				"current": "CHA",
				"max": "",
				"id": "-KoAFtkoSAxjBSKpiQVH"
			},
			{
				"name": "repeating_skill_-KoAFth6W6cZv-ga5Rze_storage_name",
				"current": "RELIGION",
				"max": "",
				"id": "-KoAFtkuhrQkTUlQVmpV"
			},
			{
				"name": "repeating_skill_-KoAFth6W6cZv-ga5Rze_name",
				"current": "Religion",
				"max": "",
				"id": "-KoAFtkyco60-6X0Y-ik"
			},
			{
				"name": "repeating_skill_-KoAFth6W6cZv-ga5Rze_ability",
				"current": "INT",
				"max": "",
				"id": "-KoAFtl10Q2Ww7k36tMm"
			},
			{
				"name": "repeating_skill_-KoAFth6W6cZv-ga5Rzf_storage_name",
				"current": "SLEIGHTOFHAND",
				"max": "",
				"id": "-KoAFtl5d8R7DnZQBW9Q"
			},
			{
				"name": "repeating_skill_-KoAFth6W6cZv-ga5Rzf_name",
				"current": "Sleight of Hand",
				"max": "",
				"id": "-KoAFtl9OemB-Z5M3Kui"
			},
			{
				"name": "repeating_skill_-KoAFth6W6cZv-ga5Rzf_ability",
				"current": "DEX",
				"max": "",
				"id": "-KoAFtlEf3vLQeG0ULJ8"
			},
			{
				"name": "repeating_skill_-KoAFth6W6cZv-ga5Rzg_storage_name",
				"current": "STEALTH",
				"max": "",
				"id": "-KoAFtlIovnMUT3JweLl"
			},
			{
				"name": "repeating_skill_-KoAFth6W6cZv-ga5Rzg_name",
				"current": "Stealth",
				"max": "",
				"id": "-KoAFtlPBUJ6b0Q_PwHz"
			},
			{
				"name": "repeating_skill_-KoAFth6W6cZv-ga5Rzg_ability",
				"current": "DEX",
				"max": "",
				"id": "-KoAFtlTQdMiN7I9E377"
			},
			{
				"name": "repeating_skill_-KoAFth6W6cZv-ga5Rzh_storage_name",
				"current": "SURVIVAL",
				"max": "",
				"id": "-KoAFtlXuaEMflZJ4Ud8"
			},
			{
				"name": "repeating_skill_-KoAFth6W6cZv-ga5Rzh_name",
				"current": "Survival",
				"max": "",
				"id": "-KoAFtlcuwMajhDasp9C"
			},
			{
				"name": "repeating_skill_-KoAFth6W6cZv-ga5Rzh_ability",
				"current": "WIS",
				"max": "",
				"id": "-KoAFtlgTxJV6iqL7Peu"
			},
			{
				"name": "saving_throw_macro_var",
				"current": "[^{STRENGTH} +0](~shaped_strength_saving_throw), [^{DEXTERITY} +0](~shaped_dexterity_saving_throw), [^{CONSTITUTION} +0](~shaped_constitution_saving_throw), [^{INTELLIGENCE} +0](~shaped_intelligence_saving_throw), [^{WISDOM} +0](~shaped_wisdom_saving_throw), [^{CHARISMA} +0](~shaped_charisma_saving_throw), [^{DEATH} +0](~shaped_death_saving_throw)",
				"max": "",
				"id": "-KoAFtt3njWAFlMK1cg2"
			},
			{
				"name": "saving_throw_query_var",
				"current": "?{Saving Throw|Strength +0,{{title=Strength Saving throw&#125;&#125; {{roll1=[[@{shaped_d20}@{d20_mod} + 0[str]]]&#125;&#125;|Dexterity +0,{{title=Dexterity Saving throw&#125;&#125; {{roll1=[[@{shaped_d20}@{d20_mod} + 0[dex]]]&#125;&#125;|Constitution +0,{{title=Constitution Saving throw&#125;&#125; {{roll1=[[@{shaped_d20}@{d20_mod} + 0[con]]]&#125;&#125;|Intelligence +0,{{title=Intelligence Saving throw&#125;&#125; {{roll1=[[@{shaped_d20}@{d20_mod} + 0[int]]]&#125;&#125;|Wisdom +0,{{title=Wisdom Saving throw&#125;&#125; {{roll1=[[@{shaped_d20}@{d20_mod} + 0[wis]]]&#125;&#125;|Charisma +0,{{title=Charisma Saving throw&#125;&#125; {{roll1=[[@{shaped_d20}@{d20_mod} + 0[cha]]]&#125;&#125;|Death +0, {{title=Death Saving throw&#125;&#125; {{death_saving_throw_successes=@{death_saving_throw_successes}&#125;&#125; {{death_saving_throw_failures=@{death_saving_throw_failures}&#125;&#125; {{roll1=[[@{shaped_d20}@{d20_mod} + ]]&#125;&#125;}",
				"max": "",
				"id": "-KoAFtt6K0YvF4qQMjnW"
			},
			{
				"name": "repeating_skill_-KoAFth4EshB524jmYyt_total",
				"current": 0,
				"max": "",
				"id": "-KoAFttQJx8D9YEQqONB"
			},
			{
				"name": "repeating_skill_-KoAFth4EshB524jmYyt_total_with_sign",
				"current": "+0",
				"max": "",
				"id": "-KoAFttTGTLz_NUGm68F"
			},
			{
				"name": "repeating_skill_-KoAFth4EshB524jmYyt_formula",
				"current": "{{@{repeating_skill_-koafth4eshb524jmyyt_skill_d20}=1}} {{roll1=[[@{repeating_skill_-koafth4eshb524jmyyt_skill_d20_wrap} + 0[dex]]]}}",
				"max": "",
				"id": "-KoAFttWW7BzcSDpNUSa"
			},
			{
				"name": "repeating_skill_-KoAFth4EshB524jmYyu_total",
				"current": 0,
				"max": "",
				"id": "-KoAFttZSIEbx2PqRooL"
			},
			{
				"name": "repeating_skill_-KoAFth4EshB524jmYyu_total_with_sign",
				"current": "+0",
				"max": "",
				"id": "-KoAFttbHNshsyfik0HM"
			},
			{
				"name": "repeating_skill_-KoAFth4EshB524jmYyu_formula",
				"current": "{{@{repeating_skill_-koafth4eshb524jmyyu_skill_d20}=1}} {{roll1=[[@{repeating_skill_-koafth4eshb524jmyyu_skill_d20_wrap} + 0[wis]]]}}",
				"max": "",
				"id": "-KoAFtteTiFLgYlrX-kN"
			},
			{
				"name": "repeating_skill_-KoAFth4EshB524jmYyv_total",
				"current": 0,
				"max": "",
				"id": "-KoAFtthdjQL46TCmVap"
			},
			{
				"name": "repeating_skill_-KoAFth4EshB524jmYyv_total_with_sign",
				"current": "+0",
				"max": "",
				"id": "-KoAFttk_I797Hqz1-8i"
			},
			{
				"name": "repeating_skill_-KoAFth4EshB524jmYyv_formula",
				"current": "{{@{repeating_skill_-koafth4eshb524jmyyv_skill_d20}=1}} {{roll1=[[@{repeating_skill_-koafth4eshb524jmyyv_skill_d20_wrap} + 0[int]]]}}",
				"max": "",
				"id": "-KoAFttmiIihY1QMxNJY"
			},
			{
				"name": "repeating_skill_-KoAFth59aXPKNZYkgIg_total",
				"current": 0,
				"max": "",
				"id": "-KoAFttpYbk-J8lpRB0Z"
			},
			{
				"name": "repeating_skill_-KoAFth59aXPKNZYkgIg_total_with_sign",
				"current": "+0",
				"max": "",
				"id": "-KoAFttstjYPQB7TlUxe"
			},
			{
				"name": "repeating_skill_-KoAFth59aXPKNZYkgIg_formula",
				"current": "{{@{repeating_skill_-koafth59axpknzykgig_skill_d20}=1}} {{roll1=[[@{repeating_skill_-koafth59axpknzykgig_skill_d20_wrap} + 0[str]]]}}",
				"max": "",
				"id": "-KoAFttusIV2uHsKjCoL"
			},
			{
				"name": "repeating_skill_-KoAFth59aXPKNZYkgIh_total",
				"current": 0,
				"max": "",
				"id": "-KoAFttx-y7V5PqiDvzt"
			},
			{
				"name": "repeating_skill_-KoAFth59aXPKNZYkgIh_total_with_sign",
				"current": "+0",
				"max": "",
				"id": "-KoAFtu-sQxRSxokBmUq"
			},
			{
				"name": "repeating_skill_-KoAFth59aXPKNZYkgIh_formula",
				"current": "{{@{repeating_skill_-koafth59axpknzykgih_skill_d20}=1}} {{roll1=[[@{repeating_skill_-koafth59axpknzykgih_skill_d20_wrap} + 0[cha]]]}}",
				"max": "",
				"id": "-KoAFtu2xQ5lZ6SO98QA"
			},
			{
				"name": "repeating_skill_-KoAFth59aXPKNZYkgIi_total",
				"current": 0,
				"max": "",
				"id": "-KoAFtu5Vw-KcxAkQgmV"
			},
			{
				"name": "repeating_skill_-KoAFth59aXPKNZYkgIi_total_with_sign",
				"current": "+0",
				"max": "",
				"id": "-KoAFtu89h7HDRtpaSQv"
			},
			{
				"name": "repeating_skill_-KoAFth59aXPKNZYkgIi_formula",
				"current": "{{@{repeating_skill_-koafth59axpknzykgii_skill_d20}=1}} {{roll1=[[@{repeating_skill_-koafth59axpknzykgii_skill_d20_wrap} + 0[int]]]}}",
				"max": "",
				"id": "-KoAFtuAGBnGFBvovg3K"
			},
			{
				"name": "repeating_skill_-KoAFth59aXPKNZYkgIj_total",
				"current": 0,
				"max": "",
				"id": "-KoAFtuEM4SYHFl7PA6H"
			},
			{
				"name": "repeating_skill_-KoAFth59aXPKNZYkgIj_total_with_sign",
				"current": "+0",
				"max": "",
				"id": "-KoAFtuHFF7HPZrh3Xo_"
			},
			{
				"name": "repeating_skill_-KoAFth59aXPKNZYkgIj_formula",
				"current": "{{@{repeating_skill_-koafth59axpknzykgij_skill_d20}=1}} {{roll1=[[@{repeating_skill_-koafth59axpknzykgij_skill_d20_wrap} + 0[wis]]]}}",
				"max": "",
				"id": "-KoAFtuJ4_AAPbFLvth6"
			},
			{
				"name": "repeating_skill_-KoAFth59aXPKNZYkgIk_total",
				"current": 0,
				"max": "",
				"id": "-KoAFtuM5f-b6sK3I72I"
			},
			{
				"name": "repeating_skill_-KoAFth59aXPKNZYkgIk_total_with_sign",
				"current": "+0",
				"max": "",
				"id": "-KoAFtuPe8y2T24PVk0E"
			},
			{
				"name": "repeating_skill_-KoAFth59aXPKNZYkgIk_formula",
				"current": "{{@{repeating_skill_-koafth59axpknzykgik_skill_d20}=1}} {{roll1=[[@{repeating_skill_-koafth59axpknzykgik_skill_d20_wrap} + 0[cha]]]}}",
				"max": "",
				"id": "-KoAFtuReMb1sCynzT9M"
			},
			{
				"name": "repeating_skill_-KoAFth59aXPKNZYkgIl_total",
				"current": 0,
				"max": "",
				"id": "-KoAFtuVvSrEjCkbm2zB"
			},
			{
				"name": "repeating_skill_-KoAFth59aXPKNZYkgIl_total_with_sign",
				"current": "+0",
				"max": "",
				"id": "-KoAFtuYkwi94Yrvw3-i"
			},
			{
				"name": "repeating_skill_-KoAFth59aXPKNZYkgIl_formula",
				"current": "{{@{repeating_skill_-koafth59axpknzykgil_skill_d20}=1}} {{roll1=[[@{repeating_skill_-koafth59axpknzykgil_skill_d20_wrap} + 0[int]]]}}",
				"max": "",
				"id": "-KoAFtuaeztC1-EtiXE5"
			},
			{
				"name": "repeating_skill_-KoAFth59aXPKNZYkgIm_total",
				"current": 0,
				"max": "",
				"id": "-KoAFtucVMWCjsKrNdrU"
			},
			{
				"name": "repeating_skill_-KoAFth59aXPKNZYkgIm_total_with_sign",
				"current": "+0",
				"max": "",
				"id": "-KoAFtufGvNN_yEKi28p"
			},
			{
				"name": "repeating_skill_-KoAFth59aXPKNZYkgIm_formula",
				"current": "{{@{repeating_skill_-koafth59axpknzykgim_skill_d20}=1}} {{roll1=[[@{repeating_skill_-koafth59axpknzykgim_skill_d20_wrap} + 0[wis]]]}}",
				"max": "",
				"id": "-KoAFtuiQHKpzz9OHsja"
			},
			{
				"name": "repeating_skill_-KoAFth59aXPKNZYkgIn_total",
				"current": 0,
				"max": "",
				"id": "-KoAFtulNXUUrYcEQuJ0"
			},
			{
				"name": "repeating_skill_-KoAFth59aXPKNZYkgIn_total_with_sign",
				"current": "+0",
				"max": "",
				"id": "-KoAFtuolZUiDFkuA4VZ"
			},
			{
				"name": "repeating_skill_-KoAFth59aXPKNZYkgIn_formula",
				"current": "{{@{repeating_skill_-koafth59axpknzykgin_skill_d20}=1}} {{roll1=[[@{repeating_skill_-koafth59axpknzykgin_skill_d20_wrap} + 0[int]]]}}",
				"max": "",
				"id": "-KoAFtuqkFb6L_1wzNy8"
			},
			{
				"name": "repeating_skill_-KoAFth59aXPKNZYkgIo_total",
				"current": 0,
				"max": "",
				"id": "-KoAFtutMG7O74M_fnu1"
			},
			{
				"name": "repeating_skill_-KoAFth59aXPKNZYkgIo_total_with_sign",
				"current": "+0",
				"max": "",
				"id": "-KoAFtuwTVv5o-pn45fV"
			},
			{
				"name": "repeating_skill_-KoAFth59aXPKNZYkgIo_formula",
				"current": "{{@{repeating_skill_-koafth59axpknzykgio_skill_d20}=1}} {{roll1=[[@{repeating_skill_-koafth59axpknzykgio_skill_d20_wrap} + 0[wis]]]}}",
				"max": "",
				"id": "-KoAFtuzd6fDgrinV76E"
			},
			{
				"name": "repeating_skill_-KoAFth59aXPKNZYkgIp_total",
				"current": 0,
				"max": "",
				"id": "-KoAFtv1xtITp48GMKK3"
			},
			{
				"name": "repeating_skill_-KoAFth59aXPKNZYkgIp_total_with_sign",
				"current": "+0",
				"max": "",
				"id": "-KoAFtv6ZaujAnfupSk6"
			},
			{
				"name": "repeating_skill_-KoAFth59aXPKNZYkgIp_formula",
				"current": "{{@{repeating_skill_-koafth59axpknzykgip_skill_d20}=1}} {{roll1=[[@{repeating_skill_-koafth59axpknzykgip_skill_d20_wrap} + 0[cha]]]}}",
				"max": "",
				"id": "-KoAFtv9yUQRpozWJIrE"
			},
			{
				"name": "repeating_skill_-KoAFth59aXPKNZYkgIq_total",
				"current": 0,
				"max": "",
				"id": "-KoAFtvCZIQDVHP4DlJ_"
			},
			{
				"name": "repeating_skill_-KoAFth59aXPKNZYkgIq_total_with_sign",
				"current": "+0",
				"max": "",
				"id": "-KoAFtvEcGljoDjYPxZu"
			},
			{
				"name": "repeating_skill_-KoAFth59aXPKNZYkgIq_formula",
				"current": "{{@{repeating_skill_-koafth59axpknzykgiq_skill_d20}=1}} {{roll1=[[@{repeating_skill_-koafth59axpknzykgiq_skill_d20_wrap} + 0[cha]]]}}",
				"max": "",
				"id": "-KoAFtvH9oJePe6AAG9r"
			},
			{
				"name": "repeating_skill_-KoAFth6W6cZv-ga5Rze_total",
				"current": 0,
				"max": "",
				"id": "-KoAFtvLFrAM641msQk_"
			},
			{
				"name": "repeating_skill_-KoAFth6W6cZv-ga5Rze_total_with_sign",
				"current": "+0",
				"max": "",
				"id": "-KoAFtvQEqF4Wkzh5xhu"
			},
			{
				"name": "repeating_skill_-KoAFth6W6cZv-ga5Rze_formula",
				"current": "{{@{repeating_skill_-koafth6w6czv-ga5rze_skill_d20}=1}} {{roll1=[[@{repeating_skill_-koafth6w6czv-ga5rze_skill_d20_wrap} + 0[int]]]}}",
				"max": "",
				"id": "-KoAFtvUbzIeiREzFv_B"
			},
			{
				"name": "repeating_skill_-KoAFth6W6cZv-ga5Rzf_total",
				"current": 0,
				"max": "",
				"id": "-KoAFtvX60cc3d5kRufQ"
			},
			{
				"name": "repeating_skill_-KoAFth6W6cZv-ga5Rzf_total_with_sign",
				"current": "+0",
				"max": "",
				"id": "-KoAFtva-rmpZRr0X4lF"
			},
			{
				"name": "repeating_skill_-KoAFth6W6cZv-ga5Rzf_formula",
				"current": "{{@{repeating_skill_-koafth6w6czv-ga5rzf_skill_d20}=1}} {{roll1=[[@{repeating_skill_-koafth6w6czv-ga5rzf_skill_d20_wrap} + 0[dex]]]}}",
				"max": "",
				"id": "-KoAFtvdtdEYNiyhFglh"
			},
			{
				"name": "repeating_skill_-KoAFth6W6cZv-ga5Rzg_total",
				"current": 0,
				"max": "",
				"id": "-KoAFtvi-1p0KFYv1smU"
			},
			{
				"name": "repeating_skill_-KoAFth6W6cZv-ga5Rzg_total_with_sign",
				"current": "+0",
				"max": "",
				"id": "-KoAFtvl1OvfBf_alKs7"
			},
			{
				"name": "repeating_skill_-KoAFth6W6cZv-ga5Rzg_formula",
				"current": "{{@{repeating_skill_-koafth6w6czv-ga5rzg_skill_d20}=1}} {{roll1=[[@{repeating_skill_-koafth6w6czv-ga5rzg_skill_d20_wrap} + 0[dex]]]}}",
				"max": "",
				"id": "-KoAFtvpAwsBs3vQdWt4"
			},
			{
				"name": "repeating_skill_-KoAFth6W6cZv-ga5Rzh_total",
				"current": 0,
				"max": "",
				"id": "-KoAFtvtB2W9LTFpQmHy"
			},
			{
				"name": "repeating_skill_-KoAFth6W6cZv-ga5Rzh_total_with_sign",
				"current": "+0",
				"max": "",
				"id": "-KoAFtvwdtk7RJ5XQNCs"
			},
			{
				"name": "repeating_skill_-KoAFth6W6cZv-ga5Rzh_formula",
				"current": "{{@{repeating_skill_-koafth6w6czv-ga5rzh_skill_d20}=1}} {{roll1=[[@{repeating_skill_-koafth6w6czv-ga5rzh_skill_d20_wrap} + 0[wis]]]}}",
				"max": "",
				"id": "-KoAFtvzTRdkcqhT1kZc"
			},
			{
				"name": "ability_checks_query_var",
				"current": "?{Ability Check|Strength +0,{{title=Strength Check&#125;&#125; {{roll1=[[@{shaped_d20}@{d20_mod} + 0[str]]]&#125;&#125;|Dexterity +0,{{title=Dexterity Check&#125;&#125; {{roll1=[[@{shaped_d20}@{d20_mod} + 0[dex]]]&#125;&#125;|Constitution +0,{{title=Constitution Check&#125;&#125; {{roll1=[[@{shaped_d20}@{d20_mod} + 0[con]]]&#125;&#125;|Intelligence +0,{{title=Intelligence Check&#125;&#125; {{roll1=[[@{shaped_d20}@{d20_mod} + 0[int]]]&#125;&#125;|Wisdom +0,{{title=Wisdom Check&#125;&#125; {{roll1=[[@{shaped_d20}@{d20_mod} + 0[wis]]]&#125;&#125;|Charisma +0,{{title=Charisma Check&#125;&#125; {{roll1=[[@{shaped_d20}@{d20_mod} + 0[cha]]]&#125;&#125;|Acrobatics (Dex) +0, {{title=Acrobatics (Dex)&#125;&#125; {{@{repeating_skill_-koafth4eshb524jmyyt_skill_d20}=1&#125;&#125; {{roll1=[[@{repeating_skill_-koafth4eshb524jmyyt_skill_d20_wrap} + 0[dex]]]&#125;&#125;|Animal Handling (Wis) +0, {{title=Animal Handling (Wis)&#125;&#125; {{@{repeating_skill_-koafth4eshb524jmyyu_skill_d20}=1&#125;&#125; {{roll1=[[@{repeating_skill_-koafth4eshb524jmyyu_skill_d20_wrap} + 0[wis]]]&#125;&#125;|Arcana (Int) +0, {{title=Arcana (Int)&#125;&#125; {{@{repeating_skill_-koafth4eshb524jmyyv_skill_d20}=1&#125;&#125; {{roll1=[[@{repeating_skill_-koafth4eshb524jmyyv_skill_d20_wrap} + 0[int]]]&#125;&#125;|Athletics (Str) +0, {{title=Athletics (Str)&#125;&#125; {{@{repeating_skill_-koafth59axpknzykgig_skill_d20}=1&#125;&#125; {{roll1=[[@{repeating_skill_-koafth59axpknzykgig_skill_d20_wrap} + 0[str]]]&#125;&#125;|Deception (Cha) +0, {{title=Deception (Cha)&#125;&#125; {{@{repeating_skill_-koafth59axpknzykgih_skill_d20}=1&#125;&#125; {{roll1=[[@{repeating_skill_-koafth59axpknzykgih_skill_d20_wrap} + 0[cha]]]&#125;&#125;|History (Int) +0, {{title=History (Int)&#125;&#125; {{@{repeating_skill_-koafth59axpknzykgii_skill_d20}=1&#125;&#125; {{roll1=[[@{repeating_skill_-koafth59axpknzykgii_skill_d20_wrap} + 0[int]]]&#125;&#125;|Insight (Wis) +0, {{title=Insight (Wis)&#125;&#125; {{@{repeating_skill_-koafth59axpknzykgij_skill_d20}=1&#125;&#125; {{roll1=[[@{repeating_skill_-koafth59axpknzykgij_skill_d20_wrap} + 0[wis]]]&#125;&#125;|Intimidation (Cha) +0, {{title=Intimidation (Cha)&#125;&#125; {{@{repeating_skill_-koafth59axpknzykgik_skill_d20}=1&#125;&#125; {{roll1=[[@{repeating_skill_-koafth59axpknzykgik_skill_d20_wrap} + 0[cha]]]&#125;&#125;|Investigation (Int) +0, {{title=Investigation (Int)&#125;&#125; {{@{repeating_skill_-koafth59axpknzykgil_skill_d20}=1&#125;&#125; {{roll1=[[@{repeating_skill_-koafth59axpknzykgil_skill_d20_wrap} + 0[int]]]&#125;&#125;|Medicine (Wis) +0, {{title=Medicine (Wis)&#125;&#125; {{@{repeating_skill_-koafth59axpknzykgim_skill_d20}=1&#125;&#125; {{roll1=[[@{repeating_skill_-koafth59axpknzykgim_skill_d20_wrap} + 0[wis]]]&#125;&#125;|Nature (Int) +0, {{title=Nature (Int)&#125;&#125; {{@{repeating_skill_-koafth59axpknzykgin_skill_d20}=1&#125;&#125; {{roll1=[[@{repeating_skill_-koafth59axpknzykgin_skill_d20_wrap} + 0[int]]]&#125;&#125;|Perception (Wis) +0, {{title=Perception (Wis)&#125;&#125; {{@{repeating_skill_-koafth59axpknzykgio_skill_d20}=1&#125;&#125; {{roll1=[[@{repeating_skill_-koafth59axpknzykgio_skill_d20_wrap} + 0[wis]]]&#125;&#125;|Performance (Cha) +0, {{title=Performance (Cha)&#125;&#125; {{@{repeating_skill_-koafth59axpknzykgip_skill_d20}=1&#125;&#125; {{roll1=[[@{repeating_skill_-koafth59axpknzykgip_skill_d20_wrap} + 0[cha]]]&#125;&#125;|Persuasion (Cha) +0, {{title=Persuasion (Cha)&#125;&#125; {{@{repeating_skill_-koafth59axpknzykgiq_skill_d20}=1&#125;&#125; {{roll1=[[@{repeating_skill_-koafth59axpknzykgiq_skill_d20_wrap} + 0[cha]]]&#125;&#125;|Religion (Int) +0, {{title=Religion (Int)&#125;&#125; {{@{repeating_skill_-koafth6w6czv-ga5rze_skill_d20}=1&#125;&#125; {{roll1=[[@{repeating_skill_-koafth6w6czv-ga5rze_skill_d20_wrap} + 0[int]]]&#125;&#125;|Sleight of Hand (Dex) +0, {{title=Sleight of Hand (Dex)&#125;&#125; {{@{repeating_skill_-koafth6w6czv-ga5rzf_skill_d20}=1&#125;&#125; {{roll1=[[@{repeating_skill_-koafth6w6czv-ga5rzf_skill_d20_wrap} + 0[dex]]]&#125;&#125;|Stealth (Dex) +0, {{title=Stealth (Dex)&#125;&#125; {{@{repeating_skill_-koafth6w6czv-ga5rzg_skill_d20}=1&#125;&#125; {{roll1=[[@{repeating_skill_-koafth6w6czv-ga5rzg_skill_d20_wrap} + 0[dex]]]&#125;&#125;|Survival (Wis) +0, {{title=Survival (Wis)&#125;&#125; {{@{repeating_skill_-koafth6w6czv-ga5rzh_skill_d20}=1&#125;&#125; {{roll1=[[@{repeating_skill_-koafth6w6czv-ga5rzh_skill_d20_wrap} + 0[wis]]]&#125;&#125;}",
				"max": "",
				"id": "-KoAFu-HJlZpYlDBtdo8"
			},
			{
				"name": "ability_checks_macro_var",
				"current": "[Strength +0](~shaped_strength_check), [Dexterity +0](~shaped_dexterity_check), [Constitution +0](~shaped_constitution_check), [Intelligence +0](~shaped_intelligence_check), [Wisdom +0](~shaped_wisdom_check), [Charisma +0](~shaped_charisma_check), [Acrobatics +0](~repeating_skill_-koafth4eshb524jmyyt_skill), [Animal Handling +0](~repeating_skill_-koafth4eshb524jmyyu_skill), [Arcana +0](~repeating_skill_-koafth4eshb524jmyyv_skill), [Athletics +0](~repeating_skill_-koafth59axpknzykgig_skill), [Deception +0](~repeating_skill_-koafth59axpknzykgih_skill), [History +0](~repeating_skill_-koafth59axpknzykgii_skill), [Insight +0](~repeating_skill_-koafth59axpknzykgij_skill), [Intimidation +0](~repeating_skill_-koafth59axpknzykgik_skill), [Investigation +0](~repeating_skill_-koafth59axpknzykgil_skill), [Medicine +0](~repeating_skill_-koafth59axpknzykgim_skill), [Nature +0](~repeating_skill_-koafth59axpknzykgin_skill), [Perception +0](~repeating_skill_-koafth59axpknzykgio_skill), [Performance +0](~repeating_skill_-koafth59axpknzykgip_skill), [Persuasion +0](~repeating_skill_-koafth59axpknzykgiq_skill), [Religion +0](~repeating_skill_-koafth6w6czv-ga5rze_skill), [Sleight of Hand +0](~repeating_skill_-koafth6w6czv-ga5rzf_skill), [Stealth +0](~repeating_skill_-koafth6w6czv-ga5rzg_skill), [Survival +0](~repeating_skill_-koafth6w6czv-ga5rzh_skill)",
				"max": "",
				"id": "-KoAFu-L9NFLmpq22rs-"
			},
			{
				"name": "skills_macro_var",
				"current": "[Acrobatics +0](~repeating_skill_-koafth4eshb524jmyyt_skill), [Animal Handling +0](~repeating_skill_-koafth4eshb524jmyyu_skill), [Arcana +0](~repeating_skill_-koafth4eshb524jmyyv_skill), [Athletics +0](~repeating_skill_-koafth59axpknzykgig_skill), [Deception +0](~repeating_skill_-koafth59axpknzykgih_skill), [History +0](~repeating_skill_-koafth59axpknzykgii_skill), [Insight +0](~repeating_skill_-koafth59axpknzykgij_skill), [Intimidation +0](~repeating_skill_-koafth59axpknzykgik_skill), [Investigation +0](~repeating_skill_-koafth59axpknzykgil_skill), [Medicine +0](~repeating_skill_-koafth59axpknzykgim_skill), [Nature +0](~repeating_skill_-koafth59axpknzykgin_skill), [Perception +0](~repeating_skill_-koafth59axpknzykgio_skill), [Performance +0](~repeating_skill_-koafth59axpknzykgip_skill), [Persuasion +0](~repeating_skill_-koafth59axpknzykgiq_skill), [Religion +0](~repeating_skill_-koafth6w6czv-ga5rze_skill), [Sleight of Hand +0](~repeating_skill_-koafth6w6czv-ga5rzf_skill), [Stealth +0](~repeating_skill_-koafth6w6czv-ga5rzg_skill), [Survival +0](~repeating_skill_-koafth6w6czv-ga5rzh_skill)",
				"max": "",
				"id": "-KoAFu-OJdZqrsgSpOyw"
			},
			{
				"name": "sheet_opened",
				"current": 1,
				"max": "",
				"_id": "-Ks6mWfZl7rn14kxJeZV",
				"_type": "attribute",
				"id": "-Ks6mWfZl7rn14kxJeZV"
			},
			{
				"name": "processing",
				"current": "",
				"max": "",
				"_id": "-Ks6mXN-uq3juvegW7hF",
				"_type": "attribute",
				"id": "-Ks6mXN-uq3juvegW7hF"
			},
			{
				"name": "spell_save_DC",
				"current": 10,
				"max": "",
				"_id": "-Ks6mYqyqu-pV4tUL-xT",
				"_type": "attribute",
				"id": "-Ks6mYqyqu-pV4tUL-xT"
			},
			{
				"name": "spell_save_DC_formula",
				"current": "{{saving_throw_dc=[[8 + 2[proficient]]]}}",
				"max": "",
				"_id": "-Ks6mYrG7t6C08Jf228z",
				"_type": "attribute",
				"id": "-Ks6mYrG7t6C08Jf228z"
			},
			{
				"name": "spell_to_hit_formula",
				"current": "{{attack1=[[@{shaped_d20}@{d20_mod} + 2[proficient]}]]}}",
				"max": "",
				"_id": "-Ks6mYrYOpYKi8gFRDtx",
				"_type": "attribute",
				"id": "-Ks6mYrYOpYKi8gFRDtx"
			},
			{
				"name": "weight_offense",
				"current": 0,
				"max": "",
				"_id": "-Ks6mZWCKtxYuOk49QQS",
				"_type": "attribute",
				"id": "-Ks6mZWCKtxYuOk49QQS"
			},
			{
				"name": "weight_utility",
				"current": 0,
				"max": "",
				"_id": "-Ks6mZWTNw3sPPTvomns",
				"_type": "attribute",
				"id": "-Ks6mZWTNw3sPPTvomns"
			},
			{
				"name": "weight_equipment",
				"current": 0,
				"max": "",
				"_id": "-Ks6mZX1UwEOMyYey2_J",
				"_type": "attribute",
				"id": "-Ks6mZX1UwEOMyYey2_J"
			},
			{
				"name": "ac_from_armor",
				"current": 10,
				"max": "",
				"_id": "-Ks6mZXuABNLxXPy5ra8",
				"_type": "attribute",
				"id": "-Ks6mZXuABNLxXPy5ra8"
			},
			{
				"name": "weight_armor",
				"current": 0,
				"max": "",
				"_id": "-Ks6mZYBKbevVLh03inp",
				"_type": "attribute",
				"id": "-Ks6mZYBKbevVLh03inp"
			},
			{
				"name": "weight_total",
				"current": 0,
				"max": "",
				"_id": "-Ks6mZiwReKmhZjAVEih",
				"_type": "attribute",
				"id": "-Ks6mZiwReKmhZjAVEih"
			},
			{
				"name": "AC",
				"current": 10,
				"max": "",
				"_id": "-Ks6mZkNrGDSR1aSdDKp",
				"_type": "attribute",
				"id": "-Ks6mZkNrGDSR1aSdDKp"
			},
			{
				"name": "repeating_skill_-KoAFth6W6cZv-ga5Rzg_skill_d20",
				"current": "@{shaped_d20}",
				"max": "",
				"_id": "-Ks6mZqkBn0Lr51etbe6",
				"_type": "attribute",
				"id": "-Ks6mZqkBn0Lr51etbe6"
			},
			{
				"name": "offense_macro_var",
				"current": "",
				"max": "",
				"_id": "-Ks6mZyPlLuTqqnebqkj",
				"_type": "attribute",
				"id": "-Ks6mZyPlLuTqqnebqkj"
			},
			{
				"name": "offense_chat_var",
				"current": "",
				"max": "",
				"_id": "-Ks6mZyg7rzIZorwxm_W",
				"_type": "attribute",
				"id": "-Ks6mZyg7rzIZorwxm_W"
			},
			{
				"name": "utility_macro_var",
				"current": "",
				"max": "",
				"_id": "-Ks6mZyxWAM67eyjeBtM",
				"_type": "attribute",
				"id": "-Ks6mZyxWAM67eyjeBtM"
			},
			{
				"name": "utility_chat_var",
				"current": "",
				"max": "",
				"_id": "-Ks6mZzDlA_W7tAuLN3K",
				"_type": "attribute",
				"id": "-Ks6mZzDlA_W7tAuLN3K"
			}
		]
	},
	"blobs": {
		"bio": "",
		"gmnotes": "",
		"defaulttoken": ""
	}
}